pylukinlib/__init__.py
pylukinlib/flask/__init__.py
pylukinlib/flask/blueprint/__init__.py
pylukinlib/flask/blueprint/login/__init__.py
pylukinlib/flask/blueprint/login/login-static/grey_wash_wall.png
pylukinlib/flask/blueprint/login/login-static/login.css
pylukinlib/flask/blueprint/login/login-static/padlock.png
pylukinlib/flask/blueprint/login/templates/login.html
pylukinlib-0.0.5.dist-info/DESCRIPTION.rst
pylukinlib-0.0.5.dist-info/METADATA
pylukinlib-0.0.5.dist-info/metadata.json
pylukinlib-0.0.5.dist-info/RECORD
pylukinlib-0.0.5.dist-info/top_level.txt
pylukinlib-0.0.5.dist-info/WHEEL
