Metadata-Version: 2.0
Name: pylukinlib
Version: 0.0.5
Summary: General functions, classes and blueprints
Home-page: https://github.com/arlukin/pylukinlib
Author: Daniel Lindh
Author-email: daniel.lindh@cybercow.se
License: MIT
Keywords: flask library
Platform: UNKNOWN
Classifier: Development Status :: 3 - Alpha
Classifier: Intended Audience :: Developers
Classifier: Topic :: Software Development :: Libraries :: Python Modules
Classifier: Framework :: Flask
Classifier: License :: OSI Approved :: MIT License
Classifier: Programming Language :: Python :: 2
Classifier: Programming Language :: Python :: 2.7
Requires-Dist: Flask-Login (>=0.2.11)
Requires-Dist: Flask-WTF (>=0.11)
Provides-Extra: dev
Requires-Dist: check-manifest; extra == 'dev'
Provides-Extra: test
Requires-Dist: coverage; extra == 'test'
